LICENSE
MANIFEST.in
readme.md
setup.py
bobail/__init__.py
bobail/board.py
bobail/board_initializer.py
bobail/board_searcher.py
bobail/game.py
bobail/piece.py
bobail.egg-info/PKG-INFO
bobail.egg-info/SOURCES.txt
bobail.egg-info/dependency_links.txt
bobail.egg-info/top_level.txt
test/__init__.py
test/test_game_over.py
test/test_possible_moves.py
test/test_winner.py