Metadata-Version: 2.1
Name: bobail
Version: 1.4.2
Summary: Library for playing a standard game of bobail
Home-page: https://github.com/jasondaming/bobail
Author: jasondaming
Author-email: author@example.com
License: MIT
Platform: UNKNOWN
Classifier: Programming Language :: Python :: 3
Classifier: License :: OSI Approved :: MIT License
Classifier: Operating System :: OS Independent
